promptjudge/__init__.py
promptjudge-1.0.0.dist-info/licenses/LICENSE
promptjudge-1.0.0.dist-info/METADATA
promptjudge-1.0.0.dist-info/WHEEL
promptjudge-1.0.0.dist-info/top_level.txt
promptjudge-1.0.0.dist-info/RECORD
